siftd/__init__.py
siftd/backfill.py
siftd/cli.py
siftd/cli_ask.py
siftd/cli_install.py
siftd/config.py
siftd/ids.py
siftd/math.py
siftd/model_names.py
siftd/paths.py
siftd/plugin_discovery.py
siftd/search.py
siftd/adapters/__init__.py
siftd/adapters/_jsonl.py
siftd/adapters/aider.py
siftd/adapters/claude_code.py
siftd/adapters/codex_cli.py
siftd/adapters/gemini_cli.py
siftd/adapters/registry.py
siftd/adapters/sdk.py
siftd/adapters/template.py
siftd/adapters/validation.py
siftd/api/__init__.py
siftd/api/adapters.py
siftd/api/conversations.py
siftd/api/database.py
siftd/api/doctor.py
siftd/api/export.py
siftd/api/file_refs.py
siftd/api/peek.py
siftd/api/resources.py
siftd/api/search.py
siftd/api/stats.py
siftd/api/tags.py
siftd/api/tools.py
siftd/builtin_queries/__init__.py
siftd/builtin_queries/cost.sql
siftd/builtin_queries/daily-activity.sql
siftd/builtin_queries/harness-stats.sql
siftd/builtin_queries/model-usage.sql
siftd/builtin_queries/overview.sql
siftd/builtin_queries/shell-analysis.sql
siftd/builtin_queries/tool-usage.sql
siftd/doctor/__init__.py
siftd/doctor/checks.py
siftd/doctor/runner.py
siftd/domain/__init__.py
siftd/domain/models.py
siftd/domain/shell_categories.py
siftd/domain/source.py
siftd/embeddings/__init__.py
siftd/embeddings/availability.py
siftd/embeddings/base.py
siftd/embeddings/chunker.py
siftd/embeddings/fastembed_backend.py
siftd/embeddings/indexer.py
siftd/embeddings/ollama_backend.py
siftd/ingestion/__init__.py
siftd/ingestion/discovery.py
siftd/ingestion/orchestration.py
siftd/output/__init__.py
siftd/output/formatters.py
siftd/output/registry.py
siftd/output/validation.py
siftd/peek/__init__.py
siftd/peek/reader.py
siftd/peek/scanner.py
siftd/peek/types.py
siftd/storage/__init__.py
siftd/storage/blobs.py
siftd/storage/embeddings.py
siftd/storage/filters.py
siftd/storage/fts.py
siftd/storage/migrate_blobs.py
siftd/storage/queries.py
siftd/storage/schema.sql
siftd/storage/sql_helpers.py
siftd/storage/sqlite.py
siftd/storage/tags.py
siftd-0.3.0.dist-info/METADATA
siftd-0.3.0.dist-info/WHEEL
siftd-0.3.0.dist-info/entry_points.txt
siftd-0.3.0.dist-info/licenses/LICENSE
siftd-0.3.0.dist-info/RECORD
