Metadata-Version: 2.4
Name: siftd
Version: 0.3.0
Summary: Personal LLM usage analytics. Ingest conversation logs from CLI coding tools, query via FTS5 and semantic search.
License-Expression: MIT
License-File: LICENSE
Keywords: analytics,claude,conversation,llm,search
Classifier: Development Status :: 4 - Beta
Classifier: Environment :: Console
Classifier: Intended Audience :: Developers
Classifier: License :: OSI Approved :: MIT License
Classifier: Programming Language :: Python :: 3.12
Classifier: Topic :: Software Development :: Documentation
Requires-Python: >=3.12
Requires-Dist: httpx
Requires-Dist: loguru
Requires-Dist: numpy
Requires-Dist: pyyaml
Requires-Dist: tomlkit
Requires-Dist: tqdm
Provides-Extra: dev
Requires-Dist: pytest>=8.0; extra == 'dev'
Requires-Dist: ruff>=0.4; extra == 'dev'
Requires-Dist: ty; extra == 'dev'
Provides-Extra: embed
Requires-Dist: fastembed; extra == 'embed'
Requires-Dist: huggingface-hub; extra == 'embed'
Requires-Dist: numpy; extra == 'embed'
Requires-Dist: onnxruntime; extra == 'embed'
Requires-Dist: tokenizers; extra == 'embed'
